launcher/__init__.py
launcher/config_fields.py
launcher/config_helper.py
launcher/data_builder.py
launcher/data_source.py
launcher/data_units.py
launcher/env_parser.py
launcher/main.py
launcher/model_helper.py
launcher/model_source.py
launcher/predictor.py
launcher/rabit_context.py
launcher/tracker.py
launcher/utils.py
launcher/version.py
launcher/data_sources/__init__.py
launcher/data_sources/local/__init__.py
launcher/data_sources/local/csv_data_source.py
launcher/data_sources/odps/__init__.py
launcher/data_sources/odps/odps_data_source.py
launcher/data_sources/odps/odps_reading_helper.py
launcher/data_sources/odps/odps_utils.py
launcher/data_sources/odps/odps_writing_helper.py
launcher/model_sources/__init__.py
launcher/model_sources/local_model_source.py
launcher/model_sources/oss_model_source.py
xgboost_launcher-0.0.3.dist-info/METADATA
xgboost_launcher-0.0.3.dist-info/WHEEL
xgboost_launcher-0.0.3.dist-info/top_level.txt
xgboost_launcher-0.0.3.dist-info/RECORD
