Metadata-Version: 2.1
Name: xgboost-launcher
Version: 0.0.3
Summary: XGBoost Launcher Package
Home-page: https://github.com/alipay/ant-xgboost
Maintainer: Xu Xiao
Maintainer-email: lovedreamf@gmail.com
License: Apache-2.0
Platform: UNKNOWN
Classifier: License :: OSI Approved :: Apache Software License
Classifier: Development Status :: 5 - Production/Stable
Classifier: Operating System :: OS Independent
Classifier: Programming Language :: Python
Classifier: Programming Language :: Python :: 3
Classifier: Programming Language :: Python :: 3.6
Classifier: Programming Language :: Python :: 3.7
Requires-Python: >=3.6
Requires-Dist: ant-xgboost (==0.91)
Requires-Dist: pandas (==0.23.0)
Requires-Dist: pyyaml
Requires-Dist: psutil
Requires-Dist: oss2
Requires-Dist: pyodps
